dnv/__init__.py
dnv/onecompute/__init__.py
dnv/onecompute/authenticator.py
dnv/onecompute/azure_blob_storage_file_service.py
dnv/onecompute/bearer_auth.py
dnv/onecompute/enums.py
dnv/onecompute/environment.py
dnv/onecompute/event.py
dnv/onecompute/file_service.py
dnv/onecompute/file_specification.py
dnv/onecompute/flowmodel.py
dnv/onecompute/host_file_service.py
dnv/onecompute/http_retry_transport.py
dnv/onecompute/httpx_client.py
dnv/onecompute/job_info.py
dnv/onecompute/job_monitor.py
dnv/onecompute/json_utils.py
dnv/onecompute/local_workflow_runtime_service_manager.py
dnv/onecompute/one_compute_client.py
dnv/onecompute/one_compute_webapi.py
dnv/onecompute/result.py
dnv/onecompute/web_apis_template.py
dnv/onecompute/work_item_info.py
dnv/onecompute/work_item_properties.py
dnv/onecompute/work_item_storage_info.py
dnv/onecompute/work_status.py
dnv/onecompute/utils/__init__.py
dnv/onecompute/utils/_file_service.py
dnv/onecompute/utils/_file_size.py
dnv/onecompute/utils/_progress_reporter.py
dnv/onecompute/utils/md5_calculator.py
dnv_onecompute-12.0.0.dist-info/licenses/LICENSE
dnv_onecompute-12.0.0.dist-info/METADATA
dnv_onecompute-12.0.0.dist-info/WHEEL
dnv_onecompute-12.0.0.dist-info/top_level.txt
dnv_onecompute-12.0.0.dist-info/RECORD
