Metadata-Version: 2.4
Name: dnv-onecompute
Version: 12.0.0
Summary: Python package for seamless integration with OneCompute Platform. Streamline job management, workflows, and file operations using intuitive REST APIs. Monitor job progress and efficiently handle file uploads and downloads.
Author-email: DNV AS <software.support@dnv.com>
License: MIT License
Project-URL: Homepage, https://onecompute.dnv.com/docs/userguide
Project-URL: Changelog, https://onecompute.dnv.com/docs/userguide/guide/ReleaseNotes.html
Project-URL: Documentation, https://onecompute.dnv.com/docs
Keywords: onecompute,workflow
Classifier: License :: OSI Approved :: MIT License
Classifier: Programming Language :: Python
Classifier: Programming Language :: Python :: 3.10
Requires-Python: >=3.10
License-File: LICENSE
Requires-Dist: azure-storage-blob>=12.28.0
Requires-Dist: cancel-token==0.1.6
Requires-Dist: casefy==1.1.0
Requires-Dist: dacite==1.9.2
Requires-Dist: httpx==0.28.1
Requires-Dist: msal>=1.34.0
Requires-Dist: msal-extensions>=1.3.1
Requires-Dist: overrides==7.7.0
Requires-Dist: psutil==7.0.0
Requires-Dist: python-dateutil==2.8.2
Requires-Dist: retry==0.9.2
Requires-Dist: setuptools==80.9.0
Dynamic: license-file
